{
  "parent": "minecraft:recipes/root",
  "rewards": {
    "recipes": [
      "minecraft:smooth_stone"
    ]
  },
  "criteria": {
    "has_crafted": {
      "trigger": "minecraft:inventory_changed",
      "conditions": {
        "items": [
          {
            "tag": "additionalcolors:smooth_stone_base"
          }
        ]
      }
    },
    "has_the_recipe": {
      "trigger": "minecraft:recipe_unlocked",
      "conditions": {
        "recipe": "minecraft:smooth_stone"
      }
    }
  },
  "requirements": [
    [
      "has_crafted",
      "has_the_recipe"
    ]
  ]
}